<?xml version="1.0" encoding="UTF-8"?>
<preferences>
 <debug showDebugMenu="0" />
 <systemtable>
  <columns>
   <connections preferredWidth="111" />
   <irq preferredWidth="34" />
  </columns>
 </systemtable>
 <clocktable>
  <columns>
   <clockname preferredWidth="511" />
   <clocksource preferredWidth="511" />
   <frequency preferredWidth="492" />
  </columns>
 </clocktable>
 <library
   expandedCategories="Library/Peripherals/Debug and Performance,Library/Peripherals,Library/Microcontroller Peripherals,Project,Library,Library/Peripherals/Microcontroller Peripherals" />
 <window width="1936" height="1056" x="-8" y="-8" />
</preferences>
